Metadata-Version: 2.1
Name: odoo11-addon-mis-builder-cash-flow
Version: 11.0.1.1.0.99.dev9
Summary: MIS Builder Cash Flow
Home-page: https://github.com/OCA/mis-builder
Author: ADHOC SA, Odoo Community Association (OCA)
Author-email: support@odoo-community.org
License: LGPL-3
Platform: UNKNOWN
Classifier: Programming Language :: Python
Classifier: Framework :: Odoo
Classifier: Framework :: Odoo :: 11.0
Classifier: License :: OSI Approved :: GNU Lesser General Public License v3 (LGPLv3)
Classifier: Development Status :: 4 - Beta
Requires-Python: >=2.7, !=3.0.*, !=3.1.*, !=3.2.*, !=3.3.*, !=3.4.*
Requires-Dist: odoo11-addon-mis-builder
Requires-Dist: odoo <11.1dev,>=11.0a
